{
  "emptyIdentifier": 1,
  "findProjectByClick": {
    "click": 109,
    "core": 9.9,
    "createtime": "测试内容91q4",
    "endTime": "测试内容36v3",
    "id": "5cd2cff0e87148f8a0de012a918381c2",
    "name": "hello world9",
    "pId": "ee8f7838917a4dcb8b5f57a08981fb17",
    "picurl": "测试内容2fk9",
    "satrtTime": "测试内容622c",
    "status": 1
  },
  "findProjectPollList": {
    "id": "2f164573b41d48dba733e2e2515cb000",
    "poll": 46803,
    "projectId": "ce1124abf7e643ffa7a1748d19898373",
    "projectName": "项目投票1",
    "status": 1
  },
  "prodjectEvalList": {
    "createtime": 1516723200000,
    "evaluation": "项目专访32132146456461411咕咕咕咕过过过过过过过过过过过过过过过过过过过过过过过过过过过过过过过过过过过过过",
    "id": "111",
    "pId": "1111111",
    "pName": "哈哈哈",
    "title": "项目专访"
  },
  "projectByTimeDescList": {
    "click": 109,
    "core": 9.9,
    "createtime": "测试内容876z",
    "endTime": "测试内容z142",
    "id": "5cd2cff0e87148f8a0de012a918381c2",
    "name": "hello world9",
    "pId": "ee8f7838917a4dcb8b5f57a08981fb17",
    "picurl": "测试内容5726",
    "satrtTime": "测试内容e8v3",
    "status": 1
  }
}
